repyability/__init__.py
repyability/non_repairable.py
repyability/repairable.py
repyability/rbd/__init__.py
repyability/rbd/helper_classes.py
repyability/rbd/min_cut_sets.py
repyability/rbd/min_path_sets.py
repyability/rbd/rbd.py
repyability/rbd/rbd_args_check.py
repyability/rbd/rbd_graph.py
repyability/rbd/repairable_rbd.py
repyability/tests/__init__.py
repyability/tests/conftest.py
repyability/tests/fixed_probability.py
repyability/tests/test_non_repairable.py
repyability/tests/test_rbd_get_min_cut_sets.py
repyability/tests/test_rbd_get_min_path_sets.py
repyability/tests/test_rbd_importances.py
repyability/tests/test_rbd_koon.py
repyability/tests/test_rbd_misc.py
repyability/tests/test_rbd_sf.py
repyability/tests/test_repairable.py
repyability/tests/test_repairable_rbd.py
repyability-0.4.1.dist-info/LICENSE
repyability-0.4.1.dist-info/METADATA
repyability-0.4.1.dist-info/WHEEL
repyability-0.4.1.dist-info/top_level.txt
repyability-0.4.1.dist-info/RECORD
