Metadata-Version: 2.1
Name: repyability
Version: 0.4.1
Summary: A reliability analysis python package
Home-page: https://github.com/derrynknife/RePyability
Author: Derryn Knife
Author-email: derryn@reliafy.com
Classifier: Programming Language :: Python :: 3
Classifier: License :: OSI Approved :: MIT License
Classifier: Operating System :: OS Independent
Requires-Python: >=3.6
License-File: LICENSE
Requires-Dist: numpy
Requires-Dist: scipy
Requires-Dist: networkx
Requires-Dist: surpyval
